README.md
pyproject.toml
setup.py
co6co.task.egg-info/PKG-INFO
co6co.task.egg-info/SOURCES.txt
co6co.task.egg-info/dependency_links.txt
co6co.task.egg-info/requires.txt
co6co.task.egg-info/top_level.txt
co6co.task.egg-info/zip-safe
co6co_task/__init__.py
co6co_task/croniter.py
co6co_task/api/__init__.py
co6co_task/api/sysTask.py
co6co_task/api/syscode.py
co6co_task/model/__init__.py
co6co_task/model/enum.py
co6co_task/model/pos/__init__.py
co6co_task/model/pos/tables.py
co6co_task/service/CustomTask.py
co6co_task/service/RouterService.py
co6co_task/service/Tasks.py
co6co_task/service/__init__.py
co6co_task/service/cron.test.py
co6co_task/view_model/__init__.py
co6co_task/view_model/components.py
co6co_task/view_model/_filters/__init__.py
co6co_task/view_model/_filters/dynamic.py
co6co_task/view_model/_filters/sysTask.py
co6co_task/view_model/systask/__init__.py
co6co_task/view_model/systask/codeView.py
co6co_task/view_model/systask/dynamicCodeView.py
co6co_task/view_model/systask/schedView.py