Metadata-Version: 2.2
Name: co6co.task
Version: 0.1.2
Summary: 任务模块
Home-page: http://github.com/co6co
Author: co6co
Author-email: co6co@qq.com
Classifier: Development Status :: 5 - Production/Stable
Classifier: Intended Audience :: Developers
Classifier: License :: OSI Approved :: MIT License
Classifier: Programming Language :: Python :: 3
Classifier: Programming Language :: Python :: 3.10
Classifier: Programming Language :: Python :: 3.11
Classifier: Programming Language :: Python :: 3.12
Classifier: Operating System :: OS Independent
Requires-Dist: APScheduler>=3.10.4
Requires-Dist: SQLAlchemy>=2.0.25
Requires-Dist: co6co>=0.0.26
Requires-Dist: co6co.sanic_ext>=0.0.9
Requires-Dist: co6co.web-db>=0.0.14
Dynamic: author
Dynamic: author-email
Dynamic: classifier
Dynamic: description
Dynamic: description-content-type
Dynamic: home-page
Dynamic: requires-dist
Dynamic: summary
